async_fifo.v
module async_fifo (
    input  wire        wr_clk,
    input  wire        rd_clk,
    input  wire        reset,

    input  wire        wr_en,
    input  wire [7:0]  wr_data,
    output wire        full,

    input  wire        rd_en,
    output reg  [7:0]  rd_data,
    output wire        empty
);

    // ---------------------------------------------
    // FIFO MEMORY (16 x 8)
    // ---------------------------------------------
    reg [7:0] mem [0:15];

    // ---------------------------------------------
    // WRITE & READ POINTERS (5-bit = 4 addr + 1 wrap)
    // ---------------------------------------------
    reg [4:0] wr_ptr_bin;
    reg [4:0] rd_ptr_bin;

    reg [4:0] wr_ptr_gray;
    reg [4:0] rd_ptr_gray;

    // ---------------------------------------------
    // SYNCHRONIZED POINTERS
    // ---------------------------------------------
    reg [4:0] rd_ptr_gray_sync1, rd_ptr_gray_sync2;
    reg [4:0] wr_ptr_gray_sync1, wr_ptr_gray_sync2;

    // ---------------------------------------------
    // BINARY → GRAY FUNCTION
    // ---------------------------------------------
    function [4:0] bin2gray(input [4:0] bin);
        bin2gray = (bin >> 1) ^ bin;
    endfunction

    // ---------------------------------------------
    // WRITE CLOCK DOMAIN
    // ---------------------------------------------
    always @(posedge wr_clk or posedge reset) begin
        if (reset) begin
            wr_ptr_bin  <= 0;
            wr_ptr_gray <= 0;
        end
        else if (wr_en && !full) begin
            mem[wr_ptr_bin[3:0]] <= wr_data;
            wr_ptr_bin  <= wr_ptr_bin + 1;
            wr_ptr_gray <= bin2gray(wr_ptr_bin + 1);
        end
    end

    // ---------------------------------------------
    // READ CLOCK DOMAIN
    // ---------------------------------------------
    always @(posedge rd_clk or posedge reset) begin
        if (reset) begin
            rd_ptr_bin  <= 0;
            rd_ptr_gray <= 0;
            rd_data     <= 0;
        end
        else if (rd_en && !empty) begin
            rd_data <= mem[rd_ptr_bin[3:0]];
            rd_ptr_bin  <= rd_ptr_bin + 1;
            rd_ptr_gray <= bin2gray(rd_ptr_bin + 1);
        end
    end

    // ---------------------------------------------
    // SYNC READ POINTER INTO WRITE CLOCK DOMAIN
    // ---------------------------------------------
    always @(posedge wr_clk or posedge reset) begin
        if (reset) begin
            rd_ptr_gray_sync1 <= 0;
            rd_ptr_gray_sync2 <= 0;
        end else begin
            rd_ptr_gray_sync1 <= rd_ptr_gray;
            rd_ptr_gray_sync2 <= rd_ptr_gray_sync1;
        end
    end

    // ---------------------------------------------
    // SYNC WRITE POINTER INTO READ CLOCK DOMAIN
    // ---------------------------------------------
    always @(posedge rd_clk or posedge reset) begin
        if (reset) begin
            wr_ptr_gray_sync1 <= 0;
            wr_ptr_gray_sync2 <= 0;
        end else begin
            wr_ptr_gray_sync1 <= wr_ptr_gray;
            wr_ptr_gray_sync2 <= wr_ptr_gray_sync1;
        end
    end

    // ---------------------------------------------
    // EMPTY FLAG
    // ---------------------------------------------
    assign empty = (rd_ptr_gray == wr_ptr_gray_sync2);

    // ---------------------------------------------
    // FULL FLAG
    // ---------------------------------------------
    assign full =
        (bin2gray(wr_ptr_bin + 1) ==
        {~rd_ptr_gray_sync2[4:3], rd_ptr_gray_sync2[2:0]});

endmodule

tb_async_fifo.v
module tb_async_fifo;

    // -----------------------------------------
    // Clock and reset
    // -----------------------------------------
    reg wr_clk = 0;
    reg rd_clk = 0;
    reg reset  = 1;

    // -----------------------------------------
    // Write interface
    // -----------------------------------------
    reg        wr_en;
    reg [7:0]  wr_data;
    wire       full;

    // -----------------------------------------
    // Read interface
    // -----------------------------------------
    reg        rd_en;
    wire [7:0] rd_data;
    wire       empty;

    // -----------------------------------------
    // DUT instantiation
    // -----------------------------------------
    async_fifo DUT (
        .wr_clk (wr_clk),
        .rd_clk (rd_clk),
        .reset  (reset),
        .wr_en  (wr_en),
        .wr_data(wr_data),
        .full   (full),
        .rd_en  (rd_en),
        .rd_data(rd_data),
        .empty  (empty)
    );

    // -----------------------------------------
    // Clock generation
    // -----------------------------------------
    always #5  wr_clk = ~wr_clk;   // Write clock: 100 MHz
    always #8  rd_clk = ~rd_clk;   // Read clock: ~62.5 MHz

    // -----------------------------------------
    // Test sequence
    // -----------------------------------------
    initial begin
        // Create waveform file
        $dumpfile("fifo.vcd");
        $dumpvars(0, tb_async_fifo);

        // Initialize
        wr_en   = 0;
        rd_en   = 0;
        wr_data = 0;

        // Apply reset
        #20 reset = 0;

        // -------------------------------
        // WRITE DATA INTO FIFO
        // -------------------------------
        repeat (10) begin
            @(posedge wr_clk);
            if (!full) begin
                wr_en   = 1;
                wr_data = wr_data + 8'h01;
            end
        end
        wr_en = 0;

        // Wait a little
        #50;

        // -------------------------------
        // READ DATA FROM FIFO
        // -------------------------------
        repeat (10) begin
            @(posedge rd_clk);
            if (!empty)
                rd_en = 1;
        end
        rd_en = 0;

        // Finish simulation
        #100;
        $finish;
    end

endmodule

fifo.vcd
$date
	Tue Feb 03 19:06:30 2026
$end
$version
	Icarus Verilog
$end
$timescale
	1s
$end
$scope module tb_async_fifo $end
$var wire 1 ! empty $end
$var wire 1 " full $end
$var wire 8 # rd_data [7:0] $end
$var reg 1 $ rd_clk $end
$var reg 1 % rd_en $end
$var reg 1 & reset $end
$var reg 1 ' wr_clk $end
$var reg 8 ( wr_data [7:0] $end
$var reg 1 ) wr_en $end
$scope module DUT $end
$var wire 1 ! empty $end
$var wire 1 " full $end
$var wire 1 * rd_clk $end
$var wire 1 + rd_en $end
$var wire 1 , reset $end
$var wire 1 - wr_clk $end
$var wire 8 . wr_data [7:0] $end
$var wire 1 / wr_en $end
$var reg 8 0 rd_data [7:0] $end
$var reg 5 1 rd_ptr_bin [4:0] $end
$var reg 5 2 rd_ptr_gray [4:0] $end
$var reg 5 3 rd_ptr_gray_sync1 [4:0] $end
$var reg 5 4 rd_ptr_gray_sync2 [4:0] $end
$var reg 5 5 wr_ptr_bin [4:0] $end
$var reg 5 6 wr_ptr_gray [4:0] $end
$var reg 5 7 wr_ptr_gray_sync1 [4:0] $end
$var reg 5 8 wr_ptr_gray_sync2 [4:0] $end
$scope function bin2gray $end
$var reg 5 9 bin [4:0] $end
$var reg 5 : bin2gray [4:0] $end
$upscope $end
$upscope $end
$upscope $end
$enddefinitions $end
#0
$dumpvars
b1 :
b1 9
b0 8
b0 7
b0 6
b0 5
b0 4
b0 3
b0 2
b0 1
b0 0
0/
b0 .
0-
1,
0+
0*
0)
b0 (
0'
1&
0%
0$
b0 #
0"
1!
$end
#5
1'
1-
#8
1$
1*
#10
0'
0-
#15
1'
1-
#16
0$
0*
#20
0'
0-
0&
0,
#24
1$
1*
#25
b11 :
b10 9
b1 6
b1 5
b1 (
b1 .
1)
1/
1'
1-
#30
0'
0-
#32
0$
0*
#35
b10 :
b11 9
b11 6
b10 5
b10 (
b10 .
1'
1-
#40
b11 7
0'
0-
1$
1*
#45
b110 :
b100 9
b10 6
b11 5
b11 (
b11 .
1'
1-
#48
0$
0*
#50
0'
0-
#55
b111 :
b101 9
b110 6
b100 5
b100 (
b100 .
1'
1-
#56
b11 8
0!
b110 7
1$
1*
#60
0'
0-
#64
0$
0*
#65
b101 :
b110 9
b111 6
b101 5
b101 (
b101 .
1'
1-
#70
0'
0-
#72
b110 8
b111 7
1$
1*
#75
b100 :
b111 9
b101 6
b110 5
b110 (
b110 .
1'
1-
#80
0'
0-
0$
0*
#85
b1100 :
b1000 9
b100 6
b111 5
b111 (
b111 .
1'
1-
#88
b111 8
b100 7
1$
1*
#90
0'
0-
#95
b1101 :
b1001 9
b1100 6
b1000 5
b1000 (
b1000 .
1'
1-
#96
0$
0*
#100
0'
0-
#104
b100 8
b1100 7
1$
1*
#105
b1111 :
b1010 9
b1101 6
b1001 5
b1001 (
b1001 .
1'
1-
#110
0'
0-
#112
0$
0*
#115
0)
0/
b1010 (
b1010 .
1'
1-
#120
b1100 8
b1101 7
0'
0-
1$
1*
#125
1'
1-
#128
0$
0*
#130
0'
0-
#135
1'
1-
#136
b1101 8
1$
1*
#140
0'
0-
#144
0$
0*
#145
1'
1-
#150
0'
0-
#152
1$
1*
#155
1'
1-
#160
0'
0-
0$
0*
#165
1'
1-
#168
b1 2
b1 1
b1 0
b1 #
b1 :
b1 9
1%
1+
1$
1*
#170
0'
0-
#175
b1 3
1'
1-
#176
0$
0*
#180
0'
0-
#184
b11 2
b10 1
b10 0
b10 #
b11 :
b10 9
1$
1*
#185
b1 4
b11 3
1'
1-
#190
0'
0-
#192
0$
0*
#195
b11 4
1'
1-
#200
b10 2
b11 1
b11 0
b11 #
b10 :
b11 9
0'
0-
1$
1*
#205
b10 3
1'
1-
#208
0$
0*
#210
0'
0-
#215
b10 4
1'
1-
#216
b110 2
b100 1
b100 0
b100 #
b110 :
b100 9
1$
1*
#220
0'
0-
#224
0$
0*
#225
b110 3
1'
1-
#230
0'
0-
#232
b111 2
b101 1
b101 0
b101 #
b111 :
b101 9
1$
1*
#235
b110 4
b111 3
1'
1-
#240
0'
0-
0$
0*
#245
b111 4
1'
1-
#248
b101 2
b110 1
b110 0
b110 #
b101 :
b110 9
1$
1*
#250
0'
0-
#255
b101 3
1'
1-
#256
0$
0*
#260
0'
0-
#264
b100 2
b111 1
b111 0
b111 #
b100 :
b111 9
1$
1*
#265
b101 4
b100 3
1'
1-
#270
0'
0-
#272
0$
0*
#275
b100 4
1'
1-
#280
b1100 2
b1000 1
b1000 0
b1000 #
b1100 :
b1000 9
0'
0-
1$
1*
#285
b1100 3
1'
1-
#288
0$
0*
#290
0'
0-
#295
b1100 4
1'
1-
#296
b1101 2
1!
b1001 1
b1001 0
b1001 #
b1101 :
b1001 9
1$
1*
#300
0'
0-
#304
0$
0*
#305
b1101 3
1'
1-
#310
0'
0-
#312
0%
0+
1$
1*
#315
b1101 4
1'
1-
