sdram_controller.v
 module sdram_controller(
    input  wire clk,
    input  wire reset,
    input  wire read_req,
    input  wire write_req,
    output reg  [2:0] sdram_cmd,
    output reg  data_valid
);

parameter IDLE      = 3'd0;
parameter ACTIVE    = 3'd1;
parameter TRCD_WAIT = 3'd2;
parameter READ      = 3'd3;
parameter WRITE     = 3'd4;
parameter TCAS_WAIT = 3'd5;
parameter PRECHARGE = 3'd6;
parameter TRP_WAIT  = 3'd7;

parameter CMD_NOP       = 3'b000;
parameter CMD_ACTIVE    = 3'b001;
parameter CMD_READ      = 3'b010;
parameter CMD_WRITE     = 3'b011;
parameter CMD_PRECHARGE = 3'b100;

parameter TRCD = 3;
parameter TCAS = 2;
parameter TRP  = 2;

reg [2:0] state;
reg [3:0] counter;

reg read_latched;
reg write_latched;

always @(posedge clk or posedge reset) begin
    if(reset) begin
        state <= IDLE;
        counter <= 0;
        sdram_cmd <= CMD_NOP;
        data_valid <= 0;
        read_latched <= 0;
        write_latched <= 0;
    end
    else begin

        if(read_req)  read_latched  <= 1;
        if(write_req) write_latched <= 1;

        data_valid <= 0;

        case(state)

        IDLE: begin
            sdram_cmd <= CMD_NOP;
            if(read_latched || write_latched) begin
                state <= ACTIVE;
                sdram_cmd <= CMD_ACTIVE;
                counter <= 0;
            end
        end

        ACTIVE: begin
            state <= TRCD_WAIT;
            sdram_cmd <= CMD_NOP;
        end

        TRCD_WAIT: begin
            counter <= counter + 1;
            if(counter == TRCD) begin
                counter <= 0;
                if(read_latched)
                    state <= READ;
                else
                    state <= WRITE;
            end
        end

        READ: begin
            sdram_cmd <= CMD_READ;
            state <= TCAS_WAIT;
        end

        TCAS_WAIT: begin
            counter <= counter + 1;
            if(counter == TCAS) begin
                counter <= 0;
                data_valid <= 1;
                read_latched <= 0;
                state <= PRECHARGE;
            end
        end

        WRITE: begin
            sdram_cmd <= CMD_WRITE;
            write_latched <= 0;
            state <= PRECHARGE;
        end

        PRECHARGE: begin
            sdram_cmd <= CMD_PRECHARGE;
            state <= TRP_WAIT;
        end

        TRP_WAIT: begin
            counter <= counter + 1;
            if(counter == TRP) begin
                counter <= 0;
                state <= IDLE;
            end
        end

        endcase
    end
end

endmodule

tb_sdram_controller.v
 module tb_sdram_controller;

reg clk = 0;
reg reset;
reg read_req;
reg write_req;

wire [2:0] sdram_cmd;
wire data_valid;

sdram_controller DUT (
    .clk(clk),
    .reset(reset),
    .read_req(read_req),
    .write_req(write_req),
    .sdram_cmd(sdram_cmd),
    .data_valid(data_valid)
);

always #5 clk = ~clk;

initial begin
    $dumpfile("sdram.vcd");
    $dumpvars(0, tb_sdram_controller);

    reset = 1;
    read_req = 0;
    write_req = 0;

    #20 reset = 0;

    // WRITE TRANSACTION
    #10 write_req = 1;
    #10 write_req = 0;

    // Wait enough time for WRITE + tRP
    #120;

    // READ TRANSACTION
    #10 read_req = 1;
    #10 read_req = 0;

    // Wait to observe data_valid (after tCAS)
    #150;

    $finish;
end

endmodule

sdram.vcd
$date
	Tue Feb 03 21:20:15 2026
$end
$version
	Icarus Verilog
$end
$timescale
	1s
$end
$scope module tb_sdram_controller $end
$var wire 1 ! data_valid $end
$var wire 3 " sdram_cmd [2:0] $end
$var reg 1 # clk $end
$var reg 1 $ read_req $end
$var reg 1 % reset $end
$var reg 1 & write_req $end
$scope module DUT $end
$var wire 1 ' clk $end
$var wire 1 ( read_req $end
$var wire 1 ) reset $end
$var wire 1 * write_req $end
$var reg 4 + counter [3:0] $end
$var reg 1 , data_valid $end
$var reg 1 - read_latched $end
$var reg 3 . sdram_cmd [2:0] $end
$var reg 3 / state [2:0] $end
$var reg 1 0 write_latched $end
$upscope $end
$upscope $end
$enddefinitions $end
#0
$dumpvars
00
b0 /
b0 .
0-
0,
b0 +
0*
1)
0(
0'
0&
1%
0$
0#
b0 "
0!
$end
#5
1#
1'
#10
0#
0'
#15
1#
1'
#20
0#
0'
0%
0)
#25
1#
1'
#30
0#
0'
1&
1*
#35
10
1#
1'
#40
0#
0'
0&
0*
#45
b1 .
b1 "
b1 /
1#
1'
#50
0#
0'
#55
b0 .
b0 "
b10 /
1#
1'
#60
0#
0'
#65
b1 +
1#
1'
#70
0#
0'
#75
b10 +
1#
1'
#80
0#
0'
#85
b11 +
1#
1'
#90
0#
0'
#95
b100 /
b0 +
1#
1'
#100
0#
0'
#105
b110 /
00
b11 .
b11 "
1#
1'
#110
0#
0'
#115
b111 /
b100 .
b100 "
1#
1'
#120
0#
0'
#125
b1 +
1#
1'
#130
0#
0'
#135
b10 +
1#
1'
#140
0#
0'
#145
b0 /
b0 +
1#
1'
#150
0#
0'
#155
b0 .
b0 "
1#
1'
#160
0#
0'
#165
1#
1'
#170
0#
0'
1$
1(
#175
1-
1#
1'
#180
0#
0'
0$
0(
#185
b1 .
b1 "
b1 /
1#
1'
#190
0#
0'
#195
b0 .
b0 "
b10 /
1#
1'
#200
0#
0'
#205
b1 +
1#
1'
#210
0#
0'
#215
b10 +
1#
1'
#220
0#
0'
#225
b11 +
1#
1'
#230
0#
0'
#235
b11 /
b0 +
1#
1'
#240
0#
0'
#245
b101 /
b10 .
b10 "
1#
1'
#250
0#
0'
#255
b1 +
1#
1'
#260
0#
0'
#265
b10 +
1#
1'
#270
0#
0'
#275
b110 /
0-
1,
1!
b0 +
1#
1'
#280
0#
0'
#285
b111 /
b100 .
b100 "
0,
0!
1#
1'
#290
0#
0'
#295
b1 +
1#
1'
#300
0#
0'
#305
b10 +
1#
1'
#310
0#
0'
#315
b0 /
b0 +
1#
1'
#320
0#
0'
#325
b0 .
b0 "
1#
1'
