sdram_controller.v
 module sdram_controller(
    input  wire clk,
    input  wire reset,
    input  wire read_req,
    input  wire write_req,
    output reg  [2:0] sdram_cmd,
    output reg  data_valid
);

parameter IDLE   = 3'd0;
parameter ACTIVE = 3'd1;
parameter WAIT   = 3'd2;
parameter READ   = 3'd3;
parameter WRITE  = 3'd4;
parameter DONE   = 3'd5;

reg [2:0] state;
reg [3:0] counter;

reg read_latched;
reg write_latched;

always @(posedge clk or posedge reset) begin
    if (reset) begin
        state <= IDLE;
        sdram_cmd <= 3'b000;
        data_valid <= 0;
        counter <= 0;
        read_latched <= 0;
        write_latched <= 0;
    end
    else begin

        if(read_req)
            read_latched <= 1;

        if(write_req)
            write_latched <= 1;

        data_valid <= 0;

        case(state)

            IDLE: begin
                if(read_latched || write_latched) begin
                    state <= ACTIVE;
                    sdram_cmd <= 3'b001;
                    counter <= 0;
                end
            end

            ACTIVE: begin
                state <= WAIT;
                sdram_cmd <= 3'b000;
            end

            WAIT: begin
                counter <= counter + 1;
                if(counter == 3) begin
                    if(read_latched)
                        state <= READ;
                    else
                        state <= WRITE;
                end
            end

            READ: begin
                sdram_cmd <= 3'b010;
                data_valid <= 1;
                read_latched <= 0;
                state <= DONE;
            end

            WRITE: begin
                sdram_cmd <= 3'b011;
                write_latched <= 0;
                state <= DONE;
            end

            DONE: begin
                sdram_cmd <= 3'b000;
                state <= IDLE;
            end

        endcase
    end
end

endmodule

tb_sdram_controller.v
 module tb_sdram_controller;

reg clk = 0;
reg reset;
reg read_req;
reg write_req;
wire [2:0] sdram_cmd;
wire data_valid;

sdram_controller dut (
    .clk(clk),
    .reset(reset),
    .read_req(read_req),
    .write_req(write_req),
    .sdram_cmd(sdram_cmd),
    .data_valid(data_valid)
);

always #5 clk = ~clk;

initial begin
    $dumpfile("sdram.vcd");
    $dumpvars(0, tb_sdram_controller);

    reset = 1;
    read_req = 0;
    write_req = 0;

    #10 reset = 0;

    #10 write_req = 1;
    #10 write_req = 0;

    #60;

    #10 read_req = 1;
    #10 read_req = 0;

    #100 $finish;
end

endmodule

sdram.vcd
$date
	Tue Feb 03 19:58:26 2026
$end
$version
	Icarus Verilog
$end
$timescale
	1s
$end
$scope module tb_sdram_controller $end
$var wire 1 ! data_valid $end
$var wire 3 " sdram_cmd [2:0] $end
$var reg 1 # clk $end
$var reg 1 $ read_req $end
$var reg 1 % reset $end
$var reg 1 & write_req $end
$scope module dut $end
$var wire 1 ' clk $end
$var wire 1 ( read_req $end
$var wire 1 ) reset $end
$var wire 1 * write_req $end
$var reg 4 + counter [3:0] $end
$var reg 1 , data_valid $end
$var reg 1 - read_latched $end
$var reg 3 . sdram_cmd [2:0] $end
$var reg 3 / state [2:0] $end
$var reg 1 0 write_latched $end
$upscope $end
$upscope $end
$enddefinitions $end
#0
$dumpvars
00
b0 /
b0 .
0-
0,
b0 +
0*
1)
0(
0'
0&
1%
0$
0#
b0 "
0!
$end
#5
1#
1'
#10
0#
0'
0%
0)
#15
1#
1'
#20
0#
0'
1&
1*
#25
10
1#
1'
#30
0#
0'
0&
0*
#35
b1 .
b1 "
b1 /
1#
1'
#40
0#
0'
#45
b0 .
b0 "
b10 /
1#
1'
#50
0#
0'
#55
b1 +
1#
1'
#60
0#
0'
#65
b10 +
1#
1'
#70
0#
0'
#75
b11 +
1#
1'
#80
0#
0'
#85
b100 /
b100 +
1#
1'
#90
0#
0'
#95
b101 /
00
b11 .
b11 "
1#
1'
#100
0#
0'
1$
1(
#105
b0 /
b0 .
b0 "
1-
1#
1'
#110
0#
0'
0$
0(
#115
b0 +
b1 .
b1 "
b1 /
1#
1'
#120
0#
0'
#125
b0 .
b0 "
b10 /
1#
1'
#130
0#
0'
#135
b1 +
1#
1'
#140
0#
0'
#145
b10 +
1#
1'
#150
0#
0'
#155
b11 +
1#
1'
#160
0#
0'
#165
b11 /
b100 +
1#
1'
#170
0#
0'
#175
b101 /
0-
1,
1!
b10 .
b10 "
1#
1'
#180
0#
0'
#185
b0 /
b0 .
b0 "
0,
0!
1#
1'
